hello_python_demo_top1.py
hello_python_demo_top2.py
hello_python_demo-1.0.3.data/data/hello_python_demo_bm/b1.txt
hello_python_demo-1.0.3.data/data/hello_python_demo_bm/b2.txt
hello_python_demo-1.0.3.data/data/hello_python_demo_cfg/data.cfg
hello_python_demo-1.0.3.data/data/hello_python_demo_sh/shell1.sh
hello_python_demo-1.0.3.data/scripts/hello_python_demo_script1.py
module1/__init__.py
module1/hello2.py
module1/hello3.py
module1/submodule1/__init__.py
module1/submodule1/hello1.py
hello_python_demo-1.0.3.dist-info/METADATA
hello_python_demo-1.0.3.dist-info/WHEEL
hello_python_demo-1.0.3.dist-info/top_level.txt
hello_python_demo-1.0.3.dist-info/RECORD
